breeze_connect/__init__.py
breeze_connect/breeze_connect.py
uat_breeze_connect-1.0.13.dist-info/LICENSE
uat_breeze_connect-1.0.13.dist-info/METADATA
uat_breeze_connect-1.0.13.dist-info/WHEEL
uat_breeze_connect-1.0.13.dist-info/top_level.txt
uat_breeze_connect-1.0.13.dist-info/RECORD
