Metadata-Version: 2.1
Name: uat-breeze-connect
Version: 1.0.13
Summary: UAT Breeze Connect
Home-page: https://github.com/pypa/sampleproject
Author: UAT Breeze Connect
Author-email: test@mail.com
License: UNKNOWN
Platform: UNKNOWN
Classifier: Programming Language :: Python :: 3
Classifier: License :: OSI Approved :: MIT License
Classifier: Operating System :: OS Independent
Requires-Python: >=3.6
Requires-Dist: python-socketio[client]
Requires-Dist: requests
